aiovaksms/__init__.py
aiovaksms/client.py
aiovaksms/exceptions/__init__.py
aiovaksms/exceptions/bad_request.py
aiovaksms/models/__init__.py
aiovaksms/models/count_number.py
aiovaksms/models/country.py
aiovaksms/models/number.py
aiovaksms/models/services.py
aiovaksms/models/sms.py
aiovaksms-3.0.2.dist-info/METADATA
aiovaksms-3.0.2.dist-info/WHEEL
aiovaksms-3.0.2.dist-info/licenses/LICENSE
aiovaksms-3.0.2.dist-info/RECORD
