Metadata-Version: 2.4
Name: aiovaksms
Version: 3.0.2
Summary: Async VakSms api wrapper for python
Project-URL: Homepage, https://github.com/AioSmsProviders/aiovaksms
Author-email: lolkof <lolkofprog@gmail.com>, kewldan <kewldanil1@gmail.com>
License:                     GNU GENERAL PUBLIC LICENSE
License-File: LICENSE
Keywords: api,number,payments,rent,vaksms
Classifier: License :: OSI Approved :: MIT License
Classifier: Programming Language :: Python
Classifier: Programming Language :: Python :: 3
Requires-Python: >=3.10
Requires-Dist: aiohttp
Requires-Dist: cachetools
Requires-Dist: pydantic
